scvelo/__init__.py
scvelo/logging.py
scvelo/read_load.py
scvelo/settings.py
scvelo/utils.py
scvelo/core/__init__.py
scvelo/core/_anndata.py
scvelo/core/_arithmetic.py
scvelo/core/_base.py
scvelo/core/_linear_models.py
scvelo/core/_metrics.py
scvelo/core/_models.py
scvelo/core/_parallelize.py
scvelo/core/_utils.py
scvelo/datasets/__init__.py
scvelo/datasets/_biomart.py
scvelo/datasets/_datasets.py
scvelo/datasets/_load.py
scvelo/datasets/_read.py
scvelo/datasets/_simulate.py
scvelo/inference/__init__.py
scvelo/inference/_metabolic_labeling.py
scvelo/plotting/__init__.py
scvelo/plotting/docs.py
scvelo/plotting/gridspec.py
scvelo/plotting/heatmap.py
scvelo/plotting/paga.py
scvelo/plotting/palettes.py
scvelo/plotting/proportions.py
scvelo/plotting/pseudotime.py
scvelo/plotting/scatter.py
scvelo/plotting/simulation.py
scvelo/plotting/summary.py
scvelo/plotting/utils.py
scvelo/plotting/velocity.py
scvelo/plotting/velocity_embedding.py
scvelo/plotting/velocity_embedding_grid.py
scvelo/plotting/velocity_embedding_stream.py
scvelo/plotting/velocity_graph.py
scvelo/preprocessing/__init__.py
scvelo/preprocessing/moments.py
scvelo/preprocessing/neighbors.py
scvelo/preprocessing/utils.py
scvelo/tools/__init__.py
scvelo/tools/_core.py
scvelo/tools/_em_model.py
scvelo/tools/_em_model_core.py
scvelo/tools/_em_model_utils.py
scvelo/tools/_steady_state_model.py
scvelo/tools/_vi_model.py
scvelo/tools/_vi_module.py
scvelo/tools/optimization.py
scvelo/tools/paga.py
scvelo/tools/rank_velocity_genes.py
scvelo/tools/run.py
scvelo/tools/score_genes_cell_cycle.py
scvelo/tools/terminal_states.py
scvelo/tools/transition_matrix.py
scvelo/tools/utils.py
scvelo/tools/velocity.py
scvelo/tools/velocity_confidence.py
scvelo/tools/velocity_embedding.py
scvelo/tools/velocity_graph.py
scvelo/tools/velocity_pseudotime.py
scvelo-0.3.2.dist-info/LICENSE
scvelo-0.3.2.dist-info/METADATA
scvelo-0.3.2.dist-info/WHEEL
scvelo-0.3.2.dist-info/top_level.txt
scvelo-0.3.2.dist-info/RECORD
