Metadata-Version: 2.1
Name: scvelo
Version: 0.3.2
Summary: RNA velocity generalized through dynamical modeling
Author: Volker Bergen, Philipp Weiler
Maintainer-email: Philipp Weiler <philipp.weiler@helmholtz-muenchen.de>
License: BSD 3-Clause License
Project-URL: Documentation, https://scvelo.readthedocs.io/
Project-URL: Source, https://github.com/theislab/scvelo
Project-URL: Home-page, https://github.com/theislab/scvelo
Keywords: RNA,velocity,single cell,transcriptomics,stochastic,dynamical
Classifier: License :: OSI Approved :: BSD License
Classifier: Development Status :: 5 - Production/Stable
Classifier: Intended Audience :: Science/Research
Classifier: Natural Language :: English
Classifier: Programming Language :: Python :: 3
Classifier: Programming Language :: Python :: 3.8
Classifier: Programming Language :: Python :: 3.9
Classifier: Programming Language :: Python :: 3.10
Classifier: Topic :: Scientific/Engineering :: Bio-Informatics
Classifier: Topic :: Scientific/Engineering :: Visualization
Requires-Python: >=3.8
License-File: LICENSE
Requires-Dist: anndata >=0.7.5
Requires-Dist: scanpy >=1.5
Requires-Dist: loompy >=2.0.12
Requires-Dist: umap-learn >=0.3.10
Requires-Dist: numba >=0.41.0
Requires-Dist: numpy >=1.17
Requires-Dist: pandas !=1.4.0,>=1.1.1
Requires-Dist: scipy >=1.4.1
Requires-Dist: scikit-learn >=0.21.2
Requires-Dist: matplotlib >=3.3.0
Provides-Extra: dev
Requires-Dist: ruff ; extra == 'dev'
Requires-Dist: black ; extra == 'dev'
Requires-Dist: isort ; extra == 'dev'
Requires-Dist: hnswlib ; extra == 'dev'
Requires-Dist: hypothesis ; extra == 'dev'
Requires-Dist: louvain ; extra == 'dev'
Requires-Dist: pre-commit >=2.9.0 ; extra == 'dev'
Requires-Dist: pybind11 ; extra == 'dev'
Requires-Dist: pytest-cov ; extra == 'dev'
Requires-Dist: igraph ; extra == 'dev'
Requires-Dist: setuptools-scm ; extra == 'dev'
Provides-Extra: docs
Requires-Dist: scanpy ; extra == 'docs'
Requires-Dist: setuptools ; extra == 'docs'
Requires-Dist: setuptools-scm ; extra == 'docs'
Requires-Dist: importlib-metadata ; extra == 'docs'
Requires-Dist: sphinx-rtd-theme >=0.3 ; extra == 'docs'
Requires-Dist: sphinx-autodoc-typehints <=1.6 ; extra == 'docs'
Requires-Dist: sphinxcontrib-bibtex >=2.3.0 ; extra == 'docs'
Requires-Dist: Jinja2 <3.1 ; extra == 'docs'
Requires-Dist: ipykernel ; extra == 'docs'
Requires-Dist: sphinx <4.0,>=1.7 ; extra == 'docs'
Requires-Dist: nbsphinx <0.8.7,>=0.7 ; extra == 'docs'
Provides-Extra: hnswlib
Requires-Dist: pybind11 ; extra == 'hnswlib'
Requires-Dist: hnswlib ; extra == 'hnswlib'
Provides-Extra: louvain
Requires-Dist: igraph ; extra == 'louvain'
Requires-Dist: louvain ; extra == 'louvain'
Provides-Extra: test
Requires-Dist: pytest ; extra == 'test'
Requires-Dist: pytest-cov ; extra == 'test'
Provides-Extra: vi
Requires-Dist: scvi-tools >=0.20.1 ; extra == 'vi'
